ez_setup.py
pycf3.py
pycf3-2022.11.dist-info/LICENSE
pycf3-2022.11.dist-info/METADATA
pycf3-2022.11.dist-info/WHEEL
pycf3-2022.11.dist-info/top_level.txt
pycf3-2022.11.dist-info/RECORD
