Metadata-Version: 2.1
Name: pycf3
Version: 2022.11
Summary: Cosmicflows Galaxy Distance-Velocity Calculator client for Python
Home-page: https://github.com/quatrope/pycf3
Author: QuatroPe
Author-email: jbc.develop@gmail.com
License: 3 Clause BSD
Keywords: astronomy,cosmicflow,Distance,Velocity,calculator
Classifier: Development Status :: 4 - Beta
Classifier: Intended Audience :: Education
Classifier: Intended Audience :: Science/Research
Classifier: License :: OSI Approved :: BSD License
Classifier: Operating System :: OS Independent
Classifier: Programming Language :: Python
Classifier: Programming Language :: Python :: 3
Classifier: Programming Language :: Python :: Implementation :: CPython
Classifier: Topic :: Scientific/Engineering
License-File: LICENSE
Requires-Dist: numpy
Requires-Dist: requests
Requires-Dist: tabulate
Requires-Dist: attrs
Requires-Dist: diskcache
Requires-Dist: custom-inherit
Requires-Dist: Deprecated
